ohsome/__init__.py
ohsome/clients.py
ohsome/constants.py
ohsome/exceptions.py
ohsome/helper.py
ohsome/response.py
ohsome/test/__init__.py
ohsome/test/cassettes/test_client/test_check_time_parameter_datetime.yaml
ohsome/test/cassettes/test_client/test_check_time_parameter_list.yaml
ohsome/test/cassettes/test_client/test_end_timestamp_as_time_input.yaml
ohsome/test/cassettes/test_client/test_format_bboxes_dataframe.yaml
ohsome/test/cassettes/test_client/test_format_bboxes_list.yaml
ohsome/test/cassettes/test_client/test_format_bcircles_dataframe.yaml
ohsome/test/cassettes/test_client/test_format_bcircles_list.yaml
ohsome/test/cassettes/test_client/test_format_bcircles_pandas.yaml
ohsome/test/cassettes/test_client/test_post_with_endpoint_string.yaml
ohsome/test/cassettes/test_client/test_user_agent.yaml
ohsome/test/cassettes/test_exceptions/test_disable_logging.yaml
ohsome/test/cassettes/test_exceptions/test_exception_connection_reset.yaml
ohsome/test/cassettes/test_exceptions/test_exception_invalid_parameters.yaml
ohsome/test/cassettes/test_exceptions/test_invalid_url.yaml
ohsome/test/cassettes/test_exceptions/test_log_bpolys.yaml
ohsome/test/cassettes/test_exceptions/test_log_curl.yaml
ohsome/test/cassettes/test_exceptions/test_timeout_error.yaml
ohsome/test/cassettes/test_response/test_all_columns_with_timestamps_to_be_without_timezone.yaml
ohsome/test/cassettes/test_response/test_contributions_centroid.yaml
ohsome/test/cassettes/test_response/test_contributions_count_density_groupbyboundary.yaml
ohsome/test/cassettes/test_response/test_contributions_latest.yaml
ohsome/test/cassettes/test_response/test_elementsFullHistory_geometry.yaml
ohsome/test/cassettes/test_response/test_elements_count.yaml
ohsome/test/cassettes/test_response/test_elements_count_groupby_boundary.yaml
ohsome/test/cassettes/test_response/test_elements_count_groupby_boundary_groupby_tag.yaml
ohsome/test/cassettes/test_response/test_elements_count_groupby_key.yaml
ohsome-0.4.0.dist-info/LICENSE
ohsome-0.4.0.dist-info/METADATA
ohsome-0.4.0.dist-info/WHEEL
ohsome-0.4.0.dist-info/RECORD
