Metadata-Version: 2.1
Name: ohsome
Version: 0.4.0
Summary: A Python client for the ohsome API
Home-page: https://github.com/GIScience/ohsome-py
License: GPL-3.0
Author: HeiGIT ohsome team
Author-email: ohsome@heigit.org
Requires-Python: >=3.10,<4.0
Classifier: License :: OSI Approved :: GNU General Public License v3 (GPLv3)
Classifier: Programming Language :: Python :: 3
Classifier: Programming Language :: Python :: 3.10
Classifier: Programming Language :: Python :: 3.11
Classifier: Programming Language :: Python :: 3.12
Classifier: Programming Language :: Python :: 3.13
Requires-Dist: curlify2 (>=2.0.0,<3.0.0)
Requires-Dist: geopandas (>=1.0.1,<2.0.0)
Requires-Dist: numpy (>=2.1.2,<3.0.0)
Requires-Dist: pandas (>=2.1.3,<3.0.0)
Requires-Dist: requests (>=2.25.1,<3.0.0)
Requires-Dist: urllib3 (>=2.0.2,<3.0.0)
Project-URL: Repository, https://github.com/GIScience/ohsome-py
